cli_app/__init__.py
cli_app/app.py
cli_app/command.py
cli_app/env.py
cli_app/helpers.py
cli_app/errors/__init__.py
cli_app/errors/command_not_found.py
cli_app/errors/error.py
cli_app-0.1.0.dist-info/LICENSE
cli_app-0.1.0.dist-info/METADATA
cli_app-0.1.0.dist-info/WHEEL
cli_app-0.1.0.dist-info/top_level.txt
cli_app-0.1.0.dist-info/RECORD
