Metadata-Version: 2.1
Name: cli-app
Version: 0.1.0
Summary: Framework for creating CLI apps using Python
Home-page: https://github.com/jsphpl/python-cli-app
Author: Joseph Paul
Author-email: joseph@sehrgute.software
License: UNKNOWN
Platform: UNKNOWN
Classifier: Programming Language :: Python :: 3
Classifier: License :: OSI Approved :: MIT License
Classifier: Operating System :: OS Independent
